discord_console/__init__.py
discord_console/identify.py
discord_console-1.1.1.dist-info/METADATA
discord_console-1.1.1.dist-info/WHEEL
discord_console-1.1.1.dist-info/top_level.txt
discord_console-1.1.1.dist-info/RECORD
