Metadata-Version: 2.1
Name: discord-console
Version: 1.1.1
Summary: get your discord.py bots appear as like its on a phone.
Home-page: https://github.com/
Author: anvil
License: MIT License
Keywords: discord.py,discord console,discord console status,discord bot console status,discord console bot status
Classifier: Programming Language :: Python
Classifier: Programming Language :: Python :: 2
Classifier: Programming Language :: Python :: 2.7
Classifier: Programming Language :: Python :: 3
Classifier: Programming Language :: Python :: 3.5
Classifier: Programming Language :: Python :: 3.6
Classifier: Programming Language :: Python :: 3.7
Classifier: Programming Language :: Python :: 3.8
Classifier: Programming Language :: Python :: 3.9
Classifier: Programming Language :: Python :: 3.10
